uvrules/__init__.py
uvrules/antarray.py
uvrules/geometry.py
uvrules/improve.py
uvrules/old_antarray.py
uvrules/plotting.py
uvrules/utils.py
uvrules/algos/__init__.py
uvrules/algos/greedy.py
uvrules/algos/hexa.py
uvrules/algos/random.py
uvrules/algos/rules.py
uvrules-0.1.1.dist-info/licenses/LICENSE
uvrules-0.1.1.dist-info/METADATA
uvrules-0.1.1.dist-info/WHEEL
uvrules-0.1.1.dist-info/top_level.txt
uvrules-0.1.1.dist-info/RECORD
