Metadata-Version: 2.4
Name: uvrules
Version: 0.1.1
Summary: Generate uv-complete radio telescope arrays with the RULES algorithm
Author: Vincent MacKay
License: MIT License
Requires-Python: >=3.8
License-File: LICENSE
Requires-Dist: numpy
Requires-Dist: scipy
Requires-Dist: matplotlib
Requires-Dist: astropy
Requires-Dist: finufft
Requires-Dist: ipython
Dynamic: license-file
